sphene/__init__.py
sphene/_clique.py
sphene/_license/licenses/gpl-3.0-standalone.html
sphene/_status/status.proc.py
sphene/_status/checks/1/status_1.py
sphene/basin/__init__.py
sphene/basin/treasury.py
sphene-1.0.7.dist-info/METADATA
sphene-1.0.7.dist-info/WHEEL
sphene-1.0.7.dist-info/entry_points.txt
sphene-1.0.7.dist-info/top_level.txt
sphene-1.0.7.dist-info/RECORD
